apiframe/__init__.py
apiframe/client.py
apiframe/exceptions.py
apiframe/http_client.py
apiframe/types.py
apiframe/services/__init__.py
apiframe/services/ai_photos.py
apiframe/services/flux.py
apiframe/services/ideogram.py
apiframe/services/kling.py
apiframe/services/luma.py
apiframe/services/media.py
apiframe/services/midjourney.py
apiframe/services/midjourney_alt.py
apiframe/services/runway.py
apiframe/services/suno.py
apiframe/services/tasks.py
apiframe/services/udio.py
apiframe_sdk-1.0.0.dist-info/licenses/LICENSE
apiframe_sdk-1.0.0.dist-info/METADATA
apiframe_sdk-1.0.0.dist-info/WHEEL
apiframe_sdk-1.0.0.dist-info/top_level.txt
apiframe_sdk-1.0.0.dist-info/RECORD
