Metadata-Version: 2.4
Name: apiframe-sdk
Version: 1.0.0
Summary: Official Python SDK for Apiframe - AI image and video generation APIs
Author: Apiframe
License-Expression: MIT
Project-URL: Homepage, https://apiframe.ai
Project-URL: Documentation, https://docs.apiframe.ai
Project-URL: Repository, https://github.com/apiframe-ai/apiframe-python-sdk
Project-URL: Bug Tracker, https://github.com/apiframe-ai/apiframe-python-sdk/issues
Project-URL: Source Code, https://github.com/apiframe-ai/apiframe-python-sdk
Keywords: apiframe,midjourney,flux,ideogram,luma,suno,udio,runway,kling,ai,image-generation,video-generation
Classifier: Development Status :: 5 - Production/Stable
Classifier: Intended Audience :: Developers
Classifier: Programming Language :: Python :: 3
Classifier: Programming Language :: Python :: 3.8
Classifier: Programming Language :: Python :: 3.9
Classifier: Programming Language :: Python :: 3.10
Classifier: Programming Language :: Python :: 3.11
Classifier: Programming Language :: Python :: 3.12
Classifier: Topic :: Software Development :: Libraries :: Python Modules
Classifier: Topic :: Multimedia :: Graphics
Classifier: Topic :: Multimedia :: Video
Requires-Python: >=3.8
License-File: LICENSE
Requires-Dist: requests>=2.31.0
Requires-Dist: typing-extensions>=4.5.0; python_version < "3.11"
Provides-Extra: dev
Requires-Dist: pytest>=7.0.0; extra == "dev"
Requires-Dist: pytest-asyncio>=0.21.0; extra == "dev"
Requires-Dist: black>=23.0.0; extra == "dev"
Requires-Dist: mypy>=1.0.0; extra == "dev"
Requires-Dist: flake8>=6.0.0; extra == "dev"
Requires-Dist: isort>=5.12.0; extra == "dev"
Dynamic: license-file
